{"cameraMode":{"drawMode":0,"name":"Shaded","section":"Shading Mode"},"sceneLighting":true,"audioPlay":false,"sceneViewState":{"showFog":true,"showMaterialUpdate":false,"showSkybox":true,"showFlares":true,"showImageEffects":true,"showParticleSystems":true},"in2DMode":false,"pivot":{"x":48.6651725769043,"y":-50.17219543457031,"z":21.274646759033204},"rotation":{"x":-0.19081148505210877,"y":-0.7417589426040649,"z":0.597766637802124,"w":-0.23680976033210755},"size":18.269750595092775,"orthographic":false}